{
    "summary": "The abstract discusses the Society for Community Research and Action (SCRA) as a leading organization for community psychologists in the U.S. and globally. It highlights the historical context of SCRA, noting that since its establishment in 1966, 54 individuals have served as president. The annual addresses from these leaders are significant as they reflect the current state of community psychology and influence its future direction. This commentary analyzes 33 presidential addresses, with a focus on three identified developmental periods in the organization's history: defining, applying, and re-imagining community psychology. The themes identified reveal tensions between the society's aspirations and its actual practices. The authors conclude by proposing reflective questions aimed at guiding SCRA's strategic planning for the future.",
    "reasoning": "The summary captures the essence of the research, focusing on the historical significance of SCRA, the impact of presidential addresses, and the identification of developmental periods in community psychology. It avoids detailing specific methodologies and instead emphasizes the overarching themes and conclusions drawn from the analysis, which aligns with the main idea presented in the abstract.",
    "feedback": {
        "methodologies_feedback": "The analysis is correct and sufficient, I have no feedback at this time.",
        "abstract_sentence_analysis_feedback": "The analysis is correct and sufficient, I have no feedback at this time."
    }
}