{
    "summary": "This research examines the impact of forest cover in upstream drainage areas on agricultural productivity in the Brazilian Amazon, particularly focusing on milk production. The study highlights that while forests play a crucial role in hydrological cycles, their effects on agriculture may vary in regions with abundant water resources. The findings suggest that upstream forests can enhance productivity, especially in smaller drainage areas, and that these effects are most pronounced during periods of water scarcity or excess. As climate change leads to more variable rainfall, the importance of Amazonian forests for sustaining local agriculture is expected to increase.",
    "reasoning": "The summary captures the main idea of the research by emphasizing the relationship between forest cover and agricultural productivity, specifically milk production, in the Brazilian Amazon. It outlines the context of the study, the significance of forests in hydrological cycles, and the implications of the findings in light of climate change. The reasoning is based on the abstract's focus on the effects of upstream forests on farming, the study's geographical context, and the broader environmental considerations discussed in the research.",
    "feedback": {
        "methodologies_feedback": "The analysis is correct and sufficient, I have no feedback at this time.",
        "abstract_sentence_analysis_feedback": "The analysis is correct and sufficient, I have no feedback at this time."
    }
}