{
    "summary": "This research investigates how environmental uncertainty within supply chains affects the financial performance of firms, particularly in the context of increased global exposure. The study highlights the negative impacts of such uncertainty on financial outcomes and explores the mediating role of entrepreneurial managerial capitalism. It emphasizes that organizations employing macro and network supply chain risk management practices can enhance decision-making and mitigate adverse financial effects stemming from environmental uncertainty. The findings have significant implications for managers and practitioners in navigating supply chain risks in a globalized economy.",
    "reasoning": "The summary encapsulates the core focus of the research, which is the relationship between environmental uncertainty and firm financial performance, while also addressing the role of managerial practices in mitigating risks. It reflects the main themes and conclusions drawn from the study without delving into the specific methodologies employed, maintaining a clear focus on the research's implications and findings.",
    "feedback": {
        "methodologies_feedback": "The analysis is correct and sufficient, I have no feedback at this time.",
        "abstract_sentence_analysis_feedback": "The analysis is correct and sufficient, I have no feedback at this time."
    }
}