{
    "summary": "This article explores the enduring positive portrayal of Franklin D. Roosevelt in film and television, emphasizing how he is depicted as an idealized leader who overcomes personal challenges and inspires the public. The research investigates the origins and reasons for this consistent image, attributing it to Roosevelt's effective leadership and media savvy, as well as the ongoing influence of his family and supporters in the entertainment industry. Despite the evolution of his portrayals across various genres since the 1970s, Roosevelt's image has remained largely unchallenged, reflecting a strong cultural consensus around his legacy.",
    "reasoning": "The summary encapsulates the main idea of the research, highlighting the focus on Roosevelt's idealized image in media and the factors contributing to its persistence. It avoids specific methodologies, instead concentrating on the narrative of how Roosevelt's portrayal has been shaped and sustained over time.",
    "feedback": {
        "methodologies_feedback": "The analysis is correct and sufficient, I have no feedback at this time.",
        "abstract_sentence_analysis_feedback": "The analysis is correct and sufficient, I have no feedback at this time."
    }
}